binonymizer/__init__.py
binonymizer/address_module.py
binonymizer/bilst_module.py
binonymizer/binonymizer.py
binonymizer/binonymizer_core.py
binonymizer/binonymizer_lite.py
binonymizer/entity.py
binonymizer/ixa_module.py
binonymizer/merger_module.py
binonymizer/regex_module.py
binonymizer/spacy_module.py
binonymizer/tmx_utils.py
binonymizer/util.py
binonymizer-0.1.1.data/scripts/binonymizer
binonymizer-0.1.1.data/scripts/binonymizer-lite
binonymizer-0.1.1.dist-info/LICENSE
binonymizer-0.1.1.dist-info/METADATA
binonymizer-0.1.1.dist-info/WHEEL
binonymizer-0.1.1.dist-info/top_level.txt
binonymizer-0.1.1.dist-info/RECORD
