Metadata-Version: 2.1
Name: binonymizer
Version: 0.1.1
Summary: Binonymizer is a tool in Python that aims at tagging personal data in a parallel corpus.
Home-page: https://github.com/bitextor/binonymizer
Author: Prompsit Language Engineering
Author-email: info@prompsit.com
Maintainer: Marta Bañón
Maintainer-email: mbanon@prompsit.com
License: GNU General Public License v3.0
Project-URL: Binonymizer on GitHub, https://github.com/bitextor/binonymizer
Project-URL: Prompsit Language Engineering, http://www.prompsit.com
Project-URL: Paracrawl, https://paracrawl.eu/
Platform: UNKNOWN
Classifier: Environment :: Console
Classifier: Intended Audience :: Science/Research
Classifier: Programming Language :: Python :: 3.6
Classifier: License :: OSI Approved :: GNU General Public License v3 (GPLv3)
Classifier: Operating System :: POSIX :: Linux
Classifier: Topic :: Scientific/Engineering :: Artificial Intelligence
Classifier: Topic :: Text Processing :: Linguistic
Classifier: Topic :: Software Development :: Libraries :: Python Modules
Classifier: Topic :: Text Processing :: Filters
Requires-Dist: certifi (==2018.11.29)
Requires-Dist: chardet (==3.0.4)
Requires-Dist: cymem (==2.0.2)
Requires-Dist: cytoolz (==0.9.0.1)
Requires-Dist: dill (==0.2.9)
Requires-Dist: idna (==2.8)
Requires-Dist: jpype1
Requires-Dist: msgpack (==0.5.6)
Requires-Dist: msgpack-numpy (==0.4.3.2)
Requires-Dist: murmurhash (==1.0.1)
Requires-Dist: numpy (==1.16.1)
Requires-Dist: plac (==0.9.6)
Requires-Dist: preshed (==2.0.1)
Requires-Dist: regex (==2018.1.10)
Requires-Dist: requests (==2.21.0)
Requires-Dist: semver (==2.8.1)
Requires-Dist: six (==1.12.0)
Requires-Dist: spacy (==2.0.18)
Requires-Dist: thinc (==6.12.1)
Requires-Dist: toolz (==0.9.0)
Requires-Dist: tqdm (==4.31.1)
Requires-Dist: ujson (==1.35)
Requires-Dist: urllib3 (==1.24.1)
Requires-Dist: wrapt (==1.10.11)
